flaskr/__init__.py
flaskr/auth.py
flaskr/blog.py
flaskr/db_commands.py
flaskr/error.py
flaskr/forms.py
flaskr/models.py
flaskr/static/style.css
flaskr/templates/base.html
flaskr/templates/auth/login.html
flaskr/templates/auth/register.html
flaskr/templates/blog/_comment.html
flaskr/templates/blog/_post.html
flaskr/templates/blog/create_comment.html
flaskr/templates/blog/create_post.html
flaskr/templates/blog/edit_profile.html
flaskr/templates/blog/index.html
flaskr/templates/blog/show_post.html
flaskr/templates/blog/user.html
flaskr/templates/error/404.html
flaskr/templates/error/500.html
tests/__init__.py
flaskr_lb-1.1.1a0.dist-info/METADATA
flaskr_lb-1.1.1a0.dist-info/WHEEL
flaskr_lb-1.1.1a0.dist-info/top_level.txt
flaskr_lb-1.1.1a0.dist-info/RECORD
