Metadata-Version: 2.1
Name: flaskr-lb
Version: 1.1.1a0
Summary: UNKNOWN
Home-page: UNKNOWN
Author: UNKNOWN
Author-email: UNKNOWN
License: UNKNOWN
Platform: UNKNOWN
Requires-Dist: flask
Requires-Dist: flask-wtf
Requires-Dist: flask-login
Requires-Dist: flask-sqlalchemy
Requires-Dist: flask-migrate
Requires-Dist: email-validator
